LICENSE
MANIFEST.in
README.rst
setup.py
geokey_cartodb/__init__.py
geokey_cartodb/models.py
geokey_cartodb/serializer.py
geokey_cartodb/urls.py
geokey_cartodb/views.py
geokey_cartodb.egg-info/PKG-INFO
geokey_cartodb.egg-info/SOURCES.txt
geokey_cartodb.egg-info/dependency_links.txt
geokey_cartodb.egg-info/top_level.txt
geokey_cartodb/migrations/0001_initial.py
geokey_cartodb/migrations/__init__.py
geokey_cartodb/templates/cartodb_index.html