Metadata-Version: 1.1
Name: geokey-cartodb
Version: 0.1.4
Summary: Provides API endpoints for CartoDB
Home-page: https://github.com/ExCiteS/geokey-cartodb
Author: ExCiteS
Author-email: excites@ucl.ac.uk
License: UNKNOWN
Download-URL: https://github.com/ExCiteS/geokey-cartodb/tarball/0.1.4
Platform: UNKNOWN
